CHANGES.md
LICENSE
README.md
appendlayer.py
setup.py
appendlayer.egg-info/PKG-INFO
appendlayer.egg-info/SOURCES.txt
appendlayer.egg-info/dependency_links.txt
appendlayer.egg-info/entry_points.txt
appendlayer.egg-info/top_level.txt