Metadata-Version: 2.1
Name: appendlayer
Version: 2.1
Summary: Append a tarball to an image in a container registry
Home-page: https://github.com/malthe/appendlayer
Author: Malthe Borch
Author-email: mborch@gmail.com
License: MIT
Platform: UNKNOWN
Classifier: Development Status :: 5 - Production/Stable
Classifier: Intended Audience :: Developers
Classifier: Programming Language :: Python
Classifier: Programming Language :: Python :: 3
License-File: LICENSE
